README.md
setup.py
youtube_livechat_messages/__init__.py
youtube_livechat_messages/api.py
youtube_livechat_messages/auth.py
youtube_livechat_messages/cursor.py
youtube_livechat_messages/models.py
youtube_livechat_messages/utils.py
youtube_livechat_messages.egg-info/PKG-INFO
youtube_livechat_messages.egg-info/SOURCES.txt
youtube_livechat_messages.egg-info/dependency_links.txt
youtube_livechat_messages.egg-info/requires.txt
youtube_livechat_messages.egg-info/top_level.txt