Metadata-Version: 1.0
Name: youtube-livechat-messages
Version: 0.1.0
Summary: Youtube LiveChatMessages API wrapper 
Home-page: https://github.com/uehara1414/youtube_livechat_messages
Author: uehara1414
Author-email: akiya.noface@gmail.com
License: UNKNOWN
Platform: UNKNOWN
